tispoon/__about__.py
tispoon/__init__.py
tispoon/__main__.py
tispoon/cli.py
tispoon/core.py
tispoon-1.0.9.dist-info/LICENSE
tispoon-1.0.9.dist-info/METADATA
tispoon-1.0.9.dist-info/WHEEL
tispoon-1.0.9.dist-info/entry_points.txt
tispoon-1.0.9.dist-info/top_level.txt
tispoon-1.0.9.dist-info/RECORD
