Metadata-Version: 2.1
Name: tispoon
Version: 1.0.9
Summary: Tistory blogging library using open API
Home-page: https://github.com/Xvezda/tispoon
Author: Xvezda
Author-email: xvezda@naver.com
License: UNKNOWN
Keywords: blog blogging openapi korean tistory library
Platform: UNKNOWN
Classifier: Natural Language :: Korean
Classifier: Topic :: Education :: Testing
Classifier: Topic :: Other/Nonlisted Topic
Classifier: Development Status :: 4 - Beta
Classifier: License :: OSI Approved :: MIT License
Classifier: Programming Language :: Python :: 2
Classifier: Programming Language :: Python :: 2.7
Classifier: Programming Language :: Python :: 3
Classifier: Programming Language :: Python :: 3.5
Classifier: Programming Language :: Python :: 3.6
Classifier: Programming Language :: Python :: 3.7
Classifier: Programming Language :: Python :: 3.8
